ndx_wearables/spec/ndx-wearables.extensions.yaml
ndx_wearables/spec/ndx-wearables.namespace.yaml
ndx_wearables/__init__.py
ndx_wearables/categorical_enums.py
ndx_wearables/wearables_classes.py
ndx_wearables-0.2.1.dist-info/METADATA
ndx_wearables-0.2.1.dist-info/WHEEL
ndx_wearables-0.2.1.dist-info/licenses/LICENSE.txt
ndx_wearables-0.2.1.dist-info/RECORD
