Metadata-Version: 2.4
Name: ndx-wearables
Version: 0.2.1
Summary: Store data from human wearables
Project-URL: Homepage, https://github.com/BCM-Neurosurgery/ndx-wearables
Project-URL: Bug Tracker, https://github.com/BCM-Neurosurgery/ndx-wearables/issues
Project-URL: Discussions, https://github.com/BCM-Neurosurgery/ndx-wearables/discussions
Project-URL: Changelog, https://github.com/BCM-Neurosurgery/ndx-wearables/blob/main/CHANGELOG.md
Author-email: Tomek Fraczek <tomek.fraczek@bcm.edu>, Nicole Guittari <nicole.guittari@jhuapl.edu>, Lauren Diaz <lauren.diaz@jhuapl.edu>, Rick Hanish <rh103@rice.edu>, Erik Johnson <erik.c.johnson@jhuapl.edu>
License: BSD-3
License-File: LICENSE.txt
Keywords: NWB,NeurodataWithoutBorders,ndx-extension,nwb-extension
Classifier: Development Status :: 4 - Beta
Classifier: Intended Audience :: Developers
Classifier: Intended Audience :: Science/Research
Classifier: License :: OSI Approved :: BSD License
Classifier: Programming Language :: Python
Classifier: Programming Language :: Python :: 3.8
Classifier: Programming Language :: Python :: 3.9
Classifier: Programming Language :: Python :: 3.10
Classifier: Programming Language :: Python :: 3.11
Classifier: Programming Language :: Python :: 3.12
Requires-Python: >=3.8
Requires-Dist: hdmf>=3.14.1
Requires-Dist: ndx-events>=0.4.0
Requires-Dist: pandas
Requires-Dist: pynwb>=2.8.0
